adapters/ccxt_loader.py
adapters/fees.py
adapters/market_replay.py
agents/__init__.py
agents/avellaneda_stoikov.py
agents/depth_mm.py
agents/inventory_mm.py
agents/mean_reversion_mm.py
agents/momentum_mm.py
agents/naive_mm.py
analysis/plot_grid_heatmaps.py
analysis/plot_metrics.py
analysis/plot_multi_asset.py
api/jobs.py
api/main.py
api/queue.py
api/utils.py
config/schema.py
env/__init__.py
env/gym_env.py
env/multi_asset_env.py
env/multi_asset_gym.py
env/simple_lob_env.py
experiments/__init__.py
experiments/evaluate_agents.py
experiments/evaluate_multi_asset.py
experiments/grid_search_inventory_mm.py
experiments/hyperopt.py
experiments/run_inventory_mm.py
experiments/train_multi_ppo.py
experiments/train_ppo.py
mmrl/__init__.py
mmrl/benchmark.py
mmrl/cli.py
mmrl/report.py
risk/manager.py
storage/duckdb.py
utils/io.py
utils/metrics.py
utils/seeding.py
mmrl-0.1.7.dist-info/METADATA
mmrl-0.1.7.dist-info/WHEEL
mmrl-0.1.7.dist-info/entry_points.txt
mmrl-0.1.7.dist-info/top_level.txt
mmrl-0.1.7.dist-info/RECORD
