Metadata-Version: 2.4
Name: mmrl
Version: 0.1.7
Summary: Market Making RL - simulation, experiments, and CLI
Author: Aviral Poddar
License-Expression: MIT
Project-URL: Homepage, https://github.com/Aviral1303/Market-Making-RL-Agent
Project-URL: Repository, https://github.com/Aviral1303/Market-Making-RL-Agent
Project-URL: Issues, https://github.com/Aviral1303/Market-Making-RL-Agent/issues
Keywords: market-making,quant,reinforcement-learning,finance,mlflow,fastapi
Classifier: Programming Language :: Python :: 3
Classifier: Operating System :: OS Independent
Classifier: Topic :: Scientific/Engineering :: Artificial Intelligence
Classifier: Intended Audience :: Science/Research
Requires-Python: >=3.10
Requires-Dist: numpy>=1.23.0
Requires-Dist: pandas>=2.3.0
Requires-Dist: PyYAML>=6.0.1
Requires-Dist: tqdm>=4.66
Requires-Dist: mlflow>=2.14
Requires-Dist: typer>=0.12
Requires-Dist: matplotlib>=3.8
Requires-Dist: seaborn>=0.13
Requires-Dist: pydantic>=2.0
Provides-Extra: api
Requires-Dist: fastapi>=0.115; extra == "api"
Requires-Dist: uvicorn[standard]>=0.30; extra == "api"
Requires-Dist: redis>=5.0; extra == "api"
Requires-Dist: rq>=1.16; extra == "api"
Requires-Dist: prometheus-client>=0.20; extra == "api"
Requires-Dist: duckdb>=1.1; extra == "api"
Provides-Extra: rl
Requires-Dist: gymnasium>=0.28; extra == "rl"
Requires-Dist: stable-baselines3>=2.3; extra == "rl"
Requires-Dist: torch>=2.3; (platform_machine != "arm64" or sys_platform != "darwin") and extra == "rl"
